text2img_bot/__init__.py
text2img_bot/__main__.py
text2img_bot/_version.py
text2img_bot/hooks.py
text2img_bot-0.2.0.dist-info/LICENSE
text2img_bot-0.2.0.dist-info/METADATA
text2img_bot-0.2.0.dist-info/WHEEL
text2img_bot-0.2.0.dist-info/entry_points.txt
text2img_bot-0.2.0.dist-info/top_level.txt
text2img_bot-0.2.0.dist-info/RECORD
